azure/mgmt/datadog/__init__.py
azure/mgmt/datadog/_configuration.py
azure/mgmt/datadog/_microsoft_datadog_client.py
azure/mgmt/datadog/_patch.py
azure/mgmt/datadog/_serialization.py
azure/mgmt/datadog/_vendor.py
azure/mgmt/datadog/_version.py
azure/mgmt/datadog/py.typed
azure/mgmt/datadog/aio/__init__.py
azure/mgmt/datadog/aio/_configuration.py
azure/mgmt/datadog/aio/_microsoft_datadog_client.py
azure/mgmt/datadog/aio/_patch.py
azure/mgmt/datadog/aio/operations/__init__.py
azure/mgmt/datadog/aio/operations/_creation_supported_operations.py
azure/mgmt/datadog/aio/operations/_marketplace_agreements_operations.py
azure/mgmt/datadog/aio/operations/_monitored_subscriptions_operations.py
azure/mgmt/datadog/aio/operations/_monitors_operations.py
azure/mgmt/datadog/aio/operations/_operations.py
azure/mgmt/datadog/aio/operations/_patch.py
azure/mgmt/datadog/aio/operations/_single_sign_on_configurations_operations.py
azure/mgmt/datadog/aio/operations/_tag_rules_operations.py
azure/mgmt/datadog/models/__init__.py
azure/mgmt/datadog/models/_microsoft_datadog_client_enums.py
azure/mgmt/datadog/models/_models_py3.py
azure/mgmt/datadog/models/_patch.py
azure/mgmt/datadog/operations/__init__.py
azure/mgmt/datadog/operations/_creation_supported_operations.py
azure/mgmt/datadog/operations/_marketplace_agreements_operations.py
azure/mgmt/datadog/operations/_monitored_subscriptions_operations.py
azure/mgmt/datadog/operations/_monitors_operations.py
azure/mgmt/datadog/operations/_operations.py
azure/mgmt/datadog/operations/_patch.py
azure/mgmt/datadog/operations/_single_sign_on_configurations_operations.py
azure/mgmt/datadog/operations/_tag_rules_operations.py
azure_mgmt_datadog-2.1.0.dist-info/LICENSE
azure_mgmt_datadog-2.1.0.dist-info/METADATA
azure_mgmt_datadog-2.1.0.dist-info/WHEEL
azure_mgmt_datadog-2.1.0.dist-info/top_level.txt
azure_mgmt_datadog-2.1.0.dist-info/RECORD
